mistralrs_metal-0.6.0.post1.dist-info/METADATA
mistralrs_metal-0.6.0.post1.dist-info/WHEEL
mistralrs/__init__.py
mistralrs/__init__.pyi
mistralrs/py.typed
mistralrs/mistralrs.cpython-311-darwin.so
mistralrs_metal-0.6.0.post1.dist-info/RECORD
