Metadata-Version: 2.3
Name: mistralrs-metal
Version: 0.6.0.post1
Classifier: Programming Language :: Rust
Classifier: Programming Language :: Python :: Implementation :: CPython
Classifier: Programming Language :: Python :: Implementation :: PyPy
Classifier: License :: OSI Approved :: MIT License
Classifier: Programming Language :: Python :: 3.10
Classifier: Programming Language :: Rust
Summary: Fast and easy LLM serving.
Keywords: machine-learning
Home-Page: https://github.com/EricLBuehler/mistral.rs
Author: Eric Buehler
License: MIT
Requires-Python: >=3.10
Project-URL: Source Code, https://github.com/EricLBuehler/mistral.rs
